[
    {
        "All Sectors": [
            {
                "Industry Name": "All Industries",
                "Market Weight": "100.00%",
                "Year To Date Return": "31.08%"
            },
            {
                "Industry Name": "Semiconductors",
                "Market Weight": "28.90%",
                "Year To Date Return": "78.80%"
            },
            {
                "Industry Name": "Software - Infrastructure",
                "Market Weight": "26.30%",
                "Year To Date Return": "16.87%"
            },
            {
                "Industry Name": "Consumer Electronics",
                "Market Weight": "17.91%",
                "Year To Date Return": "13.58%"
            },
            {
                "Industry Name": "Software - Application",
                "Market Weight": "13.21%",
                "Year To Date Return": "32.47%"
            },
            {
                "Industry Name": "Information Technology Services",
                "Market Weight": "4.64%",
                "Year To Date Return": "13.65%"
            },
            {
                "Industry Name": "Communication Equipment",
                "Market Weight": "2.34%",
                "Year To Date Return": "26.25%"
            },
            {
                "Industry Name": "Semiconductor Equipment & Materials",
                "Market Weight": "2.04%",
                "Year To Date Return": "-3.17%"
            },
            {
                "Industry Name": "Computer Hardware",
                "Market Weight": "1.90%",
                "Year To Date Return": "38.28%"
            },
            {
                "Industry Name": "Electronic Components",
                "Market Weight": "1.35%",
                "Year To Date Return": "24.96%"
            },
            {
                "Industry Name": "Scientific & Technical Instruments",
                "Market Weight": "1.02%",
                "Year To Date Return": "18.37%"
            },
            {
                "Industry Name": "Solar",
                "Market Weight": "0.22%",
                "Year To Date Return": "-36.36%"
            },
            {
                "Industry Name": "Electronics & Computer Distribution",
                "Market Weight": "0.15%",
                "Year To Date Return": "-5.09%"
            }
        ]
    },
    {
        "Name": "NVDANVIDIA Corporation",
        "Last Price": "141.98",
        "1Y Target Estimate": "151.52",
        "Market Weight": "18.59%",
        "Market Cap": "3.483T",
        "Day Change %": "-3.26%",
        "Year To Date Return": "+186.70%",
        "Average Analyst Rating": "Buy"
    },
    {
        "Name": "AAPLApple Inc.",
        "Last Price": "225.00",
        "1Y Target Estimate": "240.42",
        "Market Weight": "18.15%",
        "Market Cap": "3.401T",
        "Day Change %": "-1.41%",
        "Year To Date Return": "+16.86%",
        "Average Analyst Rating": "Buy"
    },
    {
        "Name": "MSFTMicrosoft Corporation",
        "Last Price": "415.00",
        "1Y Target Estimate": "497.60",
        "Market Weight": "16.47%",
        "Market Cap": "3.085T",
        "Day Change %": "-2.79%",
        "Year To Date Return": "+10.36%",
        "Average Analyst Rating": "Buy"
    },
    {
        "Name": "AVGOBroadcom Inc.",
        "Last Price": "164.85",
        "1Y Target Estimate": "196.42",
        "Market Weight": "4.11%",
        "Market Cap": "769.945B",
        "Day Change %": "-3.25%",
        "Year To Date Return": "+47.68%",
        "Average Analyst Rating": "Buy"
    },
    {
        "Name": "ORCLOracle Corporation",
        "Last Price": "183.74",
        "1Y Target Estimate": "181.33",
        "Market Weight": "2.72%",
        "Market Cap": "509.155B",
        "Day Change %": "-1.77%",
        "Year To Date Return": "+74.28%",
        "Average Analyst Rating": "Buy"
    },
    {
        "Name": "CRMSalesforce, Inc.",
        "Last Price": "325.26",
        "1Y Target Estimate": "319.02",
        "Market Weight": "1.66%",
        "Market Cap": "310.949B",
        "Day Change %": "-1.93%",
        "Year To Date Return": "+23.61%",
        "Average Analyst Rating": "Buy"
    },
    {
        "Name": "CSCOCisco Systems, Inc.",
        "Last Price": "57.46",
        "1Y Target Estimate": "57.24",
        "Market Weight": "1.22%",
        "Market Cap": "229.037B",
        "Day Change %": "-0.79%",
        "Year To Date Return": "+13.74%",
        "Average Analyst Rating": "Buy"
    },
    {
        "Name": "ADBEAdobe Inc.",
        "Last Price": "503.37",
        "1Y Target Estimate": "623.55",
        "Market Weight": "1.18%",
        "Market Cap": "221.583B",
        "Day Change %": "-5.00%",
        "Year To Date Return": "-15.63%",
        "Average Analyst Rating": "Buy"
    },
    {
        "Name": "ACNAccenture plc",
        "Last Price": "353.57",
        "1Y Target Estimate": "382.95",
        "Market Weight": "1.18%",
        "Market Cap": "220.93B",
        "Day Change %": "-2.35%",
        "Year To Date Return": "+0.76%",
        "Average Analyst Rating": "Buy"
    },
    {
        "Name": "AMDAdvanced Micro Devices, Inc.",
        "Last Price": "134.90",
        "1Y Target Estimate": "184.72",
        "Market Weight": "1.17%",
        "Market Cap": "218.917B",
        "Day Change %": "-2.84%",
        "Year To Date Return": "-8.49%",
        "Average Analyst Rating": "Buy"
    }
]